<?xml version="1.0" encoding="UTF-8"?>
<api context="/json" name="split" xmlns="http://ws.apache.org/ns/synapse">
    <resource methods="POST">
        <inSequence>
            <log level="full">
                <property name="log1" value="json api started"/>
            </log>
            <class name="com.example.SplittingClass"/>
            <log level="full"/>
            <payloadFactory media-type="json">
                <format>$1</format>
                <args>
                    <arg evaluator="json" expression="$ctx:Child"/>
                </args>
            </payloadFactory>
            <call>
                <endpoint>
                    <http method="post" uri-template="http://52.91.255.31:8080/ttl/generate/ttl?entityType=OrganisationMapping">
                        <suspendOnFailure>
                            <initialDuration>-1</initialDuration>
                            <progressionFactor>-1</progressionFactor>
                            <maximumDuration>0</maximumDuration>
                        </suspendOnFailure>
                        <markForSuspension>
                            <retriesBeforeSuspension>0</retriesBeforeSuspension>
                        </markForSuspension>
                    </http>
                </endpoint>
            </call>
            <log level="full">
                <property name="TTL Conversion Status" value="True"/>
            </log>
            <call>
                <endpoint>
                    <http method="post" uri-template="http://52.91.255.31:8080/insertion/insertDataIntoGraph">
                        <suspendOnFailure>
                            <initialDuration>-1</initialDuration>
                            <progressionFactor>-1</progressionFactor>
                            <maximumDuration>0</maximumDuration>
                        </suspendOnFailure>
                        <markForSuspension>
                            <retriesBeforeSuspension>0</retriesBeforeSuspension>
                        </markForSuspension>
                    </http>
                </endpoint>
            </call>
            <payloadFactory media-type="json">
                <format>$1</format>
                <args>
                    <arg evaluator="json" expression="$ctx:Parent"/>
                </args>
            </payloadFactory>
            <call>
                <endpoint>
                    <http method="post" uri-template="http://52.91.255.31:8080/ttl/generate/ttl?entityType=OrganisationMapping">
                        <suspendOnFailure>
                            <initialDuration>-1</initialDuration>
                            <progressionFactor>-1</progressionFactor>
                            <maximumDuration>0</maximumDuration>
                        </suspendOnFailure>
                        <markForSuspension>
                            <retriesBeforeSuspension>0</retriesBeforeSuspension>
                        </markForSuspension>
                    </http>
                </endpoint>
            </call>
            <log level="full">
                <property name="TTL Conversion Status" value="True"/>
            </log>
            <call>
                <endpoint>
                    <http method="post" uri-template="http://52.91.255.31:8080/insertion/insertDataIntoGraph">
                        <suspendOnFailure>
                            <initialDuration>-1</initialDuration>
                            <progressionFactor>-1</progressionFactor>
                            <maximumDuration>0</maximumDuration>
                        </suspendOnFailure>
                        <markForSuspension>
                            <retriesBeforeSuspension>0</retriesBeforeSuspension>
                        </markForSuspension>
                    </http>
                </endpoint>
            </call>
            <respond/>
        </inSequence>
        <outSequence/>
        <faultSequence/>
    </resource>
</api>
